[
	{"href":"html/list.html","src":"img/14/1.jpg","alt":"kitchen_1","name":"高档骨瓷中餐具","money":"￥399"},
	{"href":"html/list.html","src":"img/14/2.jpg","alt":"kitchen_2","name":"304不锈钢餐具","money":"￥39"},
	{"href":"html/list.html","src":"img/14/3.jpg","alt":"kitchen_3","name":"304不锈钢保温杯","money":"￥89"},
	{"href":"html/list.html","src":"img/14/4.jpg","alt":"kitchen_4","name":"多彩珐琅锅22cm","money":"￥249"},
	{"href":"html/list.html","src":"img/14/5.jpg","alt":"kitchen_5","name":"英式骨瓷咖啡具","money":"￥299"},
	{"href":"html/list.html","src":"img/14/6.jpg","alt":"kitchen_6","name":"欧式保温壶-2L","money":"￥109"},
	{"href":"html/list.html","src":"img/14/7.jpg","alt":"kitchen_7","name":"骨瓷果盘","money":"￥99"},
	{"href":"html/list.html","src":"img/14/8.jpg","alt":"kitchen_8","name":"高档骨瓷中餐具","money":"￥399"}
]